CHP/CHP.py
CHP/__init__.py
CHPython-1.0.0.dist-info/METADATA
CHPython-1.0.0.dist-info/WHEEL
CHPython-1.0.0.dist-info/top_level.txt
CHPython-1.0.0.dist-info/RECORD
