Metadata-Version: 2.1
Name: CHPython
Version: 1.0.0
Summary: Programming Language
Home-page: UNKNOWN
Author: ArMafer
Author-email: <angelshaparro@outlook.com>
License: UNKNOWN
Keywords: python
Platform: UNKNOWN
Classifier: Development Status :: 1 - Planning
Classifier: Intended Audience :: Developers
Classifier: Programming Language :: Python :: 3
Classifier: Operating System :: Microsoft :: Windows
